buildmason/__init__.py
buildmason/__main__.py
buildmason/commands.py
buildmason-0.1.0.dist-info/LICENSE
buildmason-0.1.0.dist-info/METADATA
buildmason-0.1.0.dist-info/WHEEL
buildmason-0.1.0.dist-info/entry_points.txt
buildmason-0.1.0.dist-info/top_level.txt
buildmason-0.1.0.dist-info/RECORD
