Metadata-Version: 2.1
Name: buildmason
Version: 0.1.0
Summary: A command-line tool for generating scaffolding projects with different configurations
Author-email: Abhishek Chaudhary <abhishek20144047@gmail.com>
Project-URL: Homepage, https://github.com/Worm4047/BuildMason
License-File: LICENSE
Requires-Dist: click >=8.1.3
Requires-Dist: cookiecutter >=2.5.0
